[
    {
        "name": "{{i18n:Name_ナルホド}}",
        "text": "{hideTextbox}{blip:1}{playSound:PhoenixTakeThat}{playAnimation:TakeThat_JP}{showTextbox}{courtView:defense}{blip:1}{{i18n:CE3_Final_Wrong_Evidence_0}}"
    },
    {
        "name": "{{i18n:Name_サイバンチョ}}",
        "text": "{courtView:judge}{flash}{playSound:question1}{courtSprite:judge[\"Surprised\"]}{{i18n:CE3_Final_Wrong_Evidence_1}}"
    },
    {
        "name": "{{i18n:Name_ナルホド}}",
        "text": "{courtView:defense}{courtSprite:defense[\"Abashed\"]}{{i18n:CE3_Final_Wrong_Evidence_2}}"
    },
    {
        "name": "{{i18n:Name_ミツルギ}}",
        "text": "{courtView:prosecution}{courtSprite:prosecution[\"Thinking\"]}{{i18n:CE3_Final_Wrong_Evidence_3}}"
    },
    {
        "name": "{{i18n:Name_ミツルギ}}",
        "text": "{courtSprite:prosecution[\"Pointing\"]}{{i18n:CE3_Final_Wrong_Evidence_4}}"
    },
    {
        "name": "{{i18n:Name_サイバンチョ}}",
        "text": "{hideTextbox}{courtView:judge}{courtSprite:judge[\"Nod\"]}{courtSprite:judge[\"Stern\"]}{showTextbox}{{i18n:CE3_Final_Wrong_Evidence_5}}"
    },
    {
        "name": "{{i18n:Name_マヨイ}}",
        "text": "{courtView:cocounsel}{courtSprite:cocounsel[\"Thinking_Bench\"]}{{i18n:CE3_Final_Wrong_Evidence_6}}"
    },
    {
        "name": "{{i18n:Name_ナルホド}}",
        "text": "{courtView:defense}{playSound:fail}{{i18n:CE3_Final_Wrong_Evidence_7}}"
    },
    {
        "name": "{{i18n:Name_サイバンチョ}}",
        "text": "{hideTextbox}{courtView:judge}{courtSprite:judge[\"Shake_Head\"]}{courtSprite:judge[\"Stern\"]}{showTextbox}{{i18n:CE3_Final_Wrong_Evidence_8}}{lifeMod:-2}{playSound:explosion}"
    },
    {
        "name": "{{i18n:Name_ナルホド}}",
        "text": "{courtView:defense}{courtSprite:defense[\"Sweating\"]}{{i18n:CE3_Final_Wrong_Evidence_9}}"
    },
    {
        "text": "{jumpIf:FinalPresentEvidenceFailures,CE3_Final_Present_Evidence_MiaHint}{setState:FinalPresentEvidenceFailures,true}{jump:Final_Present_Evidence}{sectionEnd}"
    }
]