[
    {
        "name": "{{i18n:Name_ナルホド}}",
        "text": "{showTextbox}{hideLifeBar}{courtSprite:defense[\"Thinking\"]}{courtView:defense}{blip:0,false}{color:lightblue}{{i18n:Mia_Hint_1_0}}"
    },
    {
        "name": "{{i18n:Name_チヒロ}}",
        "text": "{hideTextbox}{fadeOutBg:400}{fadeOutCharacter:600}{courtSprite:cocounsel[\"Mia_Normal_Bench\"]}{courtView:cocounsel}{fadeInCharacter}{blip:2,true}{showTextbox}{{i18n:Mia_Hint_1_1}}"
    },
    {
        "name": "{{i18n:Name_チヒロ}}",
        "text": "{{i18n:Mia_Hint_1_2}}"
    },
    {
        "text": "{hideTextbox}{fadeOutCharacter:600}{fadeOutBg:600}{courtView:witness}{fadeInCharacter:600}{fadeInBg:600}{returnToCE}{sectionEnd}"
    }
]